sequana_pipelines/multitax/__init__.py
sequana_pipelines/multitax/blast.py
sequana_pipelines/multitax/config.yaml
sequana_pipelines/multitax/dag.png
sequana_pipelines/multitax/data/A_R1_.fastq.gz
sequana_pipelines/multitax/data/B_R1_.fastq.gz
sequana_pipelines/multitax/data/C_R1_.fastq.gz
sequana_pipelines/multitax/data/D_R1_.fastq.gz
sequana_pipelines/multitax/data/E_R1_.fastq.gz
sequana_pipelines/multitax/data/F_R1_.fastq.gz
sequana_pipelines/multitax/data/__init__.py
sequana_pipelines/multitax/logo.png
sequana_pipelines/multitax/main.py
sequana_pipelines/multitax/multiqc_config.yaml
sequana_pipelines/multitax/multitax.rules
sequana_pipelines/multitax/schema.yaml
sequana_pipelines/multitax/tools.txt
sequana_multitax-0.14.dist-info/LICENSE
sequana_multitax-0.14.dist-info/METADATA
sequana_multitax-0.14.dist-info/WHEEL
sequana_multitax-0.14.dist-info/entry_points.txt
sequana_multitax-0.14.dist-info/RECORD
